README.txt
setup.py
UwoCalendar.egg-info/PKG-INFO
UwoCalendar.egg-info/SOURCES.txt
UwoCalendar.egg-info/dependency_links.txt
UwoCalendar.egg-info/requires.txt
UwoCalendar.egg-info/top_level.txt
uwoCalendar/__init__.py
uwoCalendar/generateIcal.py