Metadata-Version: 1.0
Name: UwoCalendar
Version: 2.1.0
Summary: Python script that grabs your schedule from student.uwo.ca and creates a handy ics file
Home-page: https://github.com/pargall/UWO-Cal
Author: Peter Argall
Author-email: peter@argall.ca
License: LICENSE.txt
Platform: UNKNOWN
